Workbook

Sheet Top 2000 Companies Financial Da
A1: Index | B1: Name | C1: Country | D1: Sales | E1: Profit | F1: Assets | G1: Market Value
A2: 0 | B2: JPMorganChase | C2: United States | D2: $252.9 B | E2: $50 B | F2: $4,090.7 B | G2: $588.1 B
A3: 1 | B3: Berkshire Hathaway | C3: United States | D3: $369 B | E3: $73.4 B | F3: $1,070 B | G3: $899.1 B
A4: 2 | B4: Saudi Arabian Oil Company (Saudi Aramco) | C4: Saudi Arabia | D4: $489.1 B | E4: $116.9 B | F4: $661.5 B | G4: $1,919.3 B
A5: 3 | B5: ICBC | C5: China | D5: $223.8 B | E5: $50.4 B | F5: $6,586 B | G5: $215.2 B
A6: 4 | B6: Bank of America | C6: United States | D6: $183.3 B | E6: $25 B | F6: $3,273.8 B | G6: $307.3 B
A7: 5 | B7: Amazon | C7: United States | D7: $590.7 B | E7: $37.7 B | F7: $531 B | G7: $1,922.1 B
A8: 6 | B8: China Construction Bank | C8: China | D8: $199.8 B | E8: $47 B | F8: $5,403.8 B | G8: $187.5 B
A9: 7 | B9: Microsoft | C9: United States | D9: $236.6 B | E9: $86.2 B | F9: $484.3 B | G9: $3,123.1 B
A10: 8 | B10: Agricultural Bank of China | C10: China | D10: $193.5 B | E10: $37.4 B | F10: $5,832.9 B | G10: $170.9 B
A11: 9 | B11: Alphabet | C11: United States | D11: $317.9 B | E11: $82.4 B | F11: $407.4 B | G11: $2,177.7 B
A12: 10 | B12: Toyota Motor | C12: Japan | D12: $311.9 B | E12: $34.2 B | F12: $595.4 B | G12: $274.9 B
A13: 11 | B13: Apple | C13: United States | D13: $381.6 B | E13: $100.4 B | F13: $337.4 B | G13: $2,911.5 B
... A2002: 2000 | B2002: Shanxi Lu'an Environmental | C2002: China | D2002: $5.1 B | E2002: $812.8 M | F2002: $11.6 B | G2002: $9 B

Sheet Companies Financial Data 2024
A1: Index | B1: Name | C1: Country | D1: Sales | E1: Profit | F1: Assets | G1: Market Value
A2: 0 | B2: JPMorganChase | C2: United States | D2: =VALUE(SUBSTITUTE(SUBSTITUTE(SUBSTITUTE('Top 2000 Companies Financial Da'!D2,"$","")," B","")," M","")) * IF(RIGHT('Top 2000 Companies Financial Da'!D2,1)="B",1000000000,1000000) -> 252900000000 | E2: =VALUE(SUBSTITUTE(SUBSTITUTE(SUBSTITUTE('Top 2000 Companies Financial Da'!E2,"$","")," B","")," M","")) * IF(RIGHT('Top 2000 Companies Financial Da'!E2,1)="B",1000000000,1000000) -> 50000000000 | F2: =VALUE(SUBSTITUTE(SUBSTITUTE(SUBSTITUTE('Top 2000 Companies Financial Da'!F2,"$","")," B","")," M","")) * IF(RIGHT('Top 2000 Companies Financial Da'!F2,1)="B",1000000000,1000000) -> 4090700000000 | G2: =VALUE(SUBSTITUTE(SUBSTITUTE(SUBSTITUTE('Top 2000 Companies Financial Da'!G2,"$","")," B","")," M","")) * IF(RIGHT('Top 2000 Companies Financial Da'!G2,1)="B",1000000000,1000000) -> 588100000000
A3: 1 | B3: Berkshire Hathaway | C3: United States | D3: =VALUE(SUBSTITUTE(SUBSTITUTE(SUBSTITUTE('Top 2000 Companies Financial Da'!D3,"$","")," B","")," M","")) * IF(RIGHT('Top 2000 Companies Financial Da'!D3,1)="B",1000000000,1000000) -> 369000000000 | E3: =VALUE(SUBSTITUTE(SUBSTITUTE(SUBSTITUTE('Top 2000 Companies Financial Da'!E3,"$","")," B","")," M","")) * IF(RIGHT('Top 2000 Companies Financial Da'!E3,1)="B",1000000000,1000000) -> 73400000000 | F3: =VALUE(SUBSTITUTE(SUBSTITUTE(SUBSTITUTE('Top 2000 Companies Financial Da'!F3,"$","")," B","")," M","")) * IF(RIGHT('Top 2000 Companies Financial Da'!F3,1)="B",1000000000,1000000) -> 1070000000000 | G3: =VALUE(SUBSTITUTE(SUBSTITUTE(SUBSTITUTE('Top 2000 Companies Financial Da'!G3,"$","")," B","")," M","")) * IF(RIGHT('Top 2000 Companies Financial Da'!G3,1)="B",1000000000,1000000) -> 899100000000
A4: 2 | B4: Saudi Arabian Oil Company (Saudi Aramco) | C4: Saudi Arabia | D4: =VALUE(SUBSTITUTE(SUBSTITUTE(SUBSTITUTE('Top 2000 Companies Financial Da'!D4,"$","")," B","")," M","")) * IF(RIGHT('Top 2000 Companies Financial Da'!D4,1)="B",1000000000,1000000) -> 489100000000 | E4: =VALUE(SUBSTITUTE(SUBSTITUTE(SUBSTITUTE('Top 2000 Companies Financial Da'!E4,"$","")," B","")," M","")) * IF(RIGHT('Top 2000 Companies Financial Da'!E4,1)="B",1000000000,1000000) -> 116900000000 | F4: =VALUE(SUBSTITUTE(SUBSTITUTE(SUBSTITUTE('Top 2000 Companies Financial Da'!F4,"$","")," B","")," M","")) * IF(RIGHT('Top 2000 Companies Financial Da'!F4,1)="B",1000000000,1000000) -> 661500000000 | G4: =VALUE(SUBSTITUTE(SUBSTITUTE(SUBSTITUTE('Top 2000 Companies Financial Da'!G4,"$","")," B","")," M","")) * IF(RIGHT('Top 2000 Companies Financial Da'!G4,1)="B",1000000000,1000000) -> 1919300000000
A5: 3 | B5: ICBC | C5: China | D5: =VALUE(SUBSTITUTE(SUBSTITUTE(SUBSTITUTE('Top 2000 Companies Financial Da'!D5,"$","")," B","")," M","")) * IF(RIGHT('Top 2000 Companies Financial Da'!D5,1)="B",1000000000,1000000) -> 223800000000 | E5: =VALUE(SUBSTITUTE(SUBSTITUTE(SUBSTITUTE('Top 2000 Companies Financial Da'!E5,"$","")," B","")," M","")) * IF(RIGHT('Top 2000 Companies Financial Da'!E5,1)="B",1000000000,1000000) -> 50400000000 | F5: =VALUE(SUBSTITUTE(SUBSTITUTE(SUBSTITUTE('Top 2000 Companies Financial Da'!F5,"$","")," B","")," M","")) * IF(RIGHT('Top 2000 Companies Financial Da'!F5,1)="B",1000000000,1000000) -> 6586000000000 | G5: =VALUE(SUBSTITUTE(SUBSTITUTE(SUBSTITUTE('Top 2000 Companies Financial Da'!G5,"$","")," B","")," M","")) * IF(RIGHT('Top 2000 Companies Financial Da'!G5,1)="B",1000000000,1000000) -> 215200000000
A6: 4 | B6: Bank of America | C6: United States | D6: =VALUE(SUBSTITUTE(SUBSTITUTE(SUBSTITUTE('Top 2000 Companies Financial Da'!D6,"$","")," B","")," M","")) * IF(RIGHT('Top 2000 Companies Financial Da'!D6,1)="B",1000000000,1000000) -> 183300000000 | E6: =VALUE(SUBSTITUTE(SUBSTITUTE(SUBSTITUTE('Top 2000 Companies Financial Da'!E6,"$","")," B","")," M","")) * IF(RIGHT('Top 2000 Companies Financial Da'!E6,1)="B",1000000000,1000000) -> 25000000000 | F6: =VALUE(SUBSTITUTE(SUBSTITUTE(SUBSTITUTE('Top 2000 Companies Financial Da'!F6,"$","")," B","")," M","")) * IF(RIGHT('Top 2000 Companies Financial Da'!F6,1)="B",1000000000,1000000) -> 3273800000000 | G6: =VALUE(SUBSTITUTE(SUBSTITUTE(SUBSTITUTE('Top 2000 Companies Financial Da'!G6,"$","")," B","")," M","")) * IF(RIGHT('Top 2000 Companies Financial Da'!G6,1)="B",1000000000,1000000) -> 307300000000
A7: 5 | B7: Amazon | C7: United States | D7: =VALUE(SUBSTITUTE(SUBSTITUTE(SUBSTITUTE('Top 2000 Companies Financial Da'!D7,"$","")," B","")," M","")) * IF(RIGHT('Top 2000 Companies Financial Da'!D7,1)="B",1000000000,1000000) -> 590700000000 | E7: =VALUE(SUBSTITUTE(SUBSTITUTE(SUBSTITUTE('Top 2000 Companies Financial Da'!E7,"$","")," B","")," M","")) * IF(RIGHT('Top 2000 Companies Financial Da'!E7,1)="B",1000000000,1000000) -> 37700000000 | F7: =VALUE(SUBSTITUTE(SUBSTITUTE(SUBSTITUTE('Top 2000 Companies Financial Da'!F7,"$","")," B","")," M","")) * IF(RIGHT('Top 2000 Companies Financial Da'!F7,1)="B",1000000000,1000000) -> 531000000000 | G7: =VALUE(SUBSTITUTE(SUBSTITUTE(SUBSTITUTE('Top 2000 Companies Financial Da'!G7,"$","")," B","")," M","")) * IF(RIGHT('Top 2000 Companies Financial Da'!G7,1)="B",1000000000,1000000) -> 1922100000000
A8: 6 | B8: China Construction Bank | C8: China | D8: =VALUE(SUBSTITUTE(SUBSTITUTE(SUBSTITUTE('Top 2000 Companies Financial Da'!D8,"$","")," B","")," M","")) * IF(RIGHT('Top 2000 Companies Financial Da'!D8,1)="B",1000000000,1000000) -> 199800000000 | E8: =VALUE(SUBSTITUTE(SUBSTITUTE(SUBSTITUTE('Top 2000 Companies Financial Da'!E8,"$","")," B","")," M","")) * IF(RIGHT('Top 2000 Companies Financial Da'!E8,1)="B",1000000000,1000000) -> 47000000000 | F8: =VALUE(SUBSTITUTE(SUBSTITUTE(SUBSTITUTE('Top 2000 Companies Financial Da'!F8,"$","")," B","")," M","")) * IF(RIGHT('Top 2000 Companies Financial Da'!F8,1)="B",1000000000,1000000) -> 5403800000000 | G8: =VALUE(SUBSTITUTE(SUBSTITUTE(SUBSTITUTE('Top 2000 Companies Financial Da'!G8,"$","")," B","")," M","")) * IF(RIGHT('Top 2000 Companies Financial Da'!G8,1)="B",1000000000,1000000) -> 187500000000
A9: 7 | B9: Microsoft | C9: United States | D9: =VALUE(SUBSTITUTE(SUBSTITUTE(SUBSTITUTE('Top 2000 Companies Financial Da'!D9,"$","")," B","")," M","")) * IF(RIGHT('Top 2000 Companies Financial Da'!D9,1)="B",1000000000,1000000) -> 236600000000 | E9: =VALUE(SUBSTITUTE(SUBSTITUTE(SUBSTITUTE('Top 2000 Companies Financial Da'!E9,"$","")," B","")," M","")) * IF(RIGHT('Top 2000 Companies Financial Da'!E9,1)="B",1000000000,1000000) -> 86200000000 | F9: =VALUE(SUBSTITUTE(SUBSTITUTE(SUBSTITUTE('Top 2000 Companies Financial Da'!F9,"$","")," B","")," M","")) * IF(RIGHT('Top 2000 Companies Financial Da'!F9,1)="B",1000000000,1000000) -> 484300000000 | G9: =VALUE(SUBSTITUTE(SUBSTITUTE(SUBSTITUTE('Top 2000 Companies Financial Da'!G9,"$","")," B","")," M","")) * IF(RIGHT('Top 2000 Companies Financial Da'!G9,1)="B",1000000000,1000000) -> 3123100000000
A10: 8 | B10: Agricultural Bank of China | C10: China | D10: =VALUE(SUBSTITUTE(SUBSTITUTE(SUBSTITUTE('Top 2000 Companies Financial Da'!D10,"$","")," B","")," M","")) * IF(RIGHT('Top 2000 Companies Financial Da'!D10,1)="B",1000000000,1000000) -> 193500000000 | E10: =VALUE(SUBSTITUTE(SUBSTITUTE(SUBSTITUTE('Top 2000 Companies Financial Da'!E10,"$","")," B","")," M","")) * IF(RIGHT('Top 2000 Companies Financial Da'!E10,1)="B",1000000000,1000000) -> 37400000000 | F10: =VALUE(SUBSTITUTE(SUBSTITUTE(SUBSTITUTE('Top 2000 Companies Financial Da'!F10,"$","")," B","")," M","")) * IF(RIGHT('Top 2000 Companies Financial Da'!F10,1)="B",1000000000,1000000) -> 5832900000000 | G10: =VALUE(SUBSTITUTE(SUBSTITUTE(SUBSTITUTE('Top 2000 Companies Financial Da'!G10,"$","")," B","")," M","")) * IF(RIGHT('Top 2000 Companies Financial Da'!G10,1)="B",1000000000,1000000) -> 170900000000
A11: 9 | B11: Alphabet | C11: United States | D11: =VALUE(SUBSTITUTE(SUBSTITUTE(SUBSTITUTE('Top 2000 Companies Financial Da'!D11,"$","")," B","")," M","")) * IF(RIGHT('Top 2000 Companies Financial Da'!D11,1)="B",1000000000,1000000) -> 317900000000 | E11: =VALUE(SUBSTITUTE(SUBSTITUTE(SUBSTITUTE('Top 2000 Companies Financial Da'!E11,"$","")," B","")," M","")) * IF(RIGHT('Top 2000 Companies Financial Da'!E11,1)="B",1000000000,1000000) -> 82400000000 | F11: =VALUE(SUBSTITUTE(SUBSTITUTE(SUBSTITUTE('Top 2000 Companies Financial Da'!F11,"$","")," B","")," M","")) * IF(RIGHT('Top 2000 Companies Financial Da'!F11,1)="B",1000000000,1000000) -> 407400000000 | G11: =VALUE(SUBSTITUTE(SUBSTITUTE(SUBSTITUTE('Top 2000 Companies Financial Da'!G11,"$","")," B","")," M","")) * IF(RIGHT('Top 2000 Companies Financial Da'!G11,1)="B",1000000000,1000000) -> 2.1777e+12
A12: 10 | B12: Toyota Motor | C12: Japan | D12: =VALUE(SUBSTITUTE(SUBSTITUTE(SUBSTITUTE('Top 2000 Companies Financial Da'!D12,"$","")," B","")," M","")) * IF(RIGHT('Top 2000 Companies Financial Da'!D12,1)="B",1000000000,1000000) -> 311900000000 | E12: =VALUE(SUBSTITUTE(SUBSTITUTE(SUBSTITUTE('Top 2000 Companies Financial Da'!E12,"$","")," B","")," M","")) * IF(RIGHT('Top 2000 Companies Financial Da'!E12,1)="B",1000000000,1000000) -> 3.42e+10 | F12: =VALUE(SUBSTITUTE(SUBSTITUTE(SUBSTITUTE('Top 2000 Companies Financial Da'!F12,"$","")," B","")," M","")) * IF(RIGHT('Top 2000 Companies Financial Da'!F12,1)="B",1000000000,1000000) -> 595400000000 | G12: =VALUE(SUBSTITUTE(SUBSTITUTE(SUBSTITUTE('Top 2000 Companies Financial Da'!G12,"$","")," B","")," M","")) * IF(RIGHT('Top 2000 Companies Financial Da'!G12,1)="B",1000000000,1000000) -> 274900000000
A13: 11 | B13: Apple | C13: United States | D13: =VALUE(SUBSTITUTE(SUBSTITUTE(SUBSTITUTE('Top 2000 Companies Financial Da'!D13,"$","")," B","")," M","")) * IF(RIGHT('Top 2000 Companies Financial Da'!D13,1)="B",1000000000,1000000) -> 381600000000 | E13: =VALUE(SUBSTITUTE(SUBSTITUTE(SUBSTITUTE('Top 2000 Companies Financial Da'!E13,"$","")," B","")," M","")) * IF(RIGHT('Top 2000 Companies Financial Da'!E13,1)="B",1000000000,1000000) -> 100400000000 | F13: =VALUE(SUBSTITUTE(SUBSTITUTE(SUBSTITUTE('Top 2000 Companies Financial Da'!F13,"$","")," B","")," M","")) * IF(RIGHT('Top 2000 Companies Financial Da'!F13,1)="B",1000000000,1000000) -> 337400000000 | G13: =VALUE(SUBSTITUTE(SUBSTITUTE(SUBSTITUTE('Top 2000 Companies Financial Da'!G13,"$","")," B","")," M","")) * IF(RIGHT('Top 2000 Companies Financial Da'!G13,1)="B",1000000000,1000000) -> 2911500000000
... A2002: 2000 | B2002: Shanxi Lu'an Environmental | C2002: China | D2002: =VALUE(SUBSTITUTE(SUBSTITUTE(SUBSTITUTE('Top 2000 Companies Financial Da'!D2002,"$","")," B","")," M","")) * IF(RIGHT('Top 2000 Companies Financial Da'!D2002,1)="B",1000000000,1000000) -> 5100000000 | E2002: =VALUE(SUBSTITUTE(SUBSTITUTE(SUBSTITUTE('Top 2000 Companies Financial Da'!E2002,"$","")," B","")," M","")) * IF(RIGHT('Top 2000 Companies Financial Da'!E2002,1)="B",1000000000,1000000) -> 812800000 | F2002: =VALUE(SUBSTITUTE(SUBSTITUTE(SUBSTITUTE('Top 2000 Companies Financial Da'!F2002,"$","")," B","")," M","")) * IF(RIGHT('Top 2000 Companies Financial Da'!F2002,1)="B",1000000000,1000000) -> 11600000000 | G2002: =VALUE(SUBSTITUTE(SUBSTITUTE(SUBSTITUTE('Top 2000 Companies Financial Da'!G2002,"$","")," B","")," M","")) * IF(RIGHT('Top 2000 Companies Financial Da'!G2002,1)="B",1000000000,1000000) -> 9000000000

Sheet README
A1: This dataset contains financial information for the top 2000 global companies in 2024. It provides key metrics to analyze the financial performance and market presence of leading companies across various industries worldwide.
A3: Unilever Placed : 49 Among all companies & 9 Among companies with related Bussness Model
A4: And This Companiess are:
A6: Direct FMCG peers
A8: Procter & Gamble (P&G) — global household & personal-care consumer products (closest match).
A10: Nestlé — food & beverage giant (strong overlap on foods/ice-cream, etc.).
A12: Strong overlap (food & beverage / consumer products)
A14: PepsiCo — snacks & beverages (overlaps with Unilever’s food/refreshment businesses).
A16: Coca-Cola — beverages (partial overlap in drinks/retail channels).
A18: Kweichow Moutai — alcoholic beverages (beverage category overlap, but premium liquor niche).
A20: Personal-care / cosmetics overlap
A22: L’Oréal — cosmetics & personal care (overlap in beauty/personal-care market).
... A28: LVMH, Hermès — luxury goods / fashion / perfumes — some overlap in beauty/perfume categories but they are luxury-focused (different business model).
